mfoci/__init__.py
mfoci/helpers/__init__.py
mfoci/helpers/fama_french.py
mfoci/helpers/filterer.py
mfoci/methods/__init__.py
mfoci/methods/factor_selector.py
mfoci/methods/foci.py
mfoci/methods/kfoci.py
mfoci/methods/lasso.py
mfoci/methods/mfoci_func.py
mfoci/methods/multivar_chatterjee.py
mfoci/response_vars/__init__.py
mfoci/response_vars/etf_vars.py
mfoci/response_vars/stock_return_vars.py
mfoci/response_vars/volatility_vars.py
mfoci-0.2.4.dist-info/licenses/LICENSE
mfoci-0.2.4.dist-info/METADATA
mfoci-0.2.4.dist-info/WHEEL
mfoci-0.2.4.dist-info/top_level.txt
mfoci-0.2.4.dist-info/RECORD
