Metadata-Version: 2.4
Name: mfoci
Version: 0.2.4
Summary: Financial market analysis tool implementing the MFOCI algorithm for factor selection
Author-email: Marcus Rockel <corram@outlook.de>
License: MIT
Project-URL: Homepage, https://github.com/Corrram/mfoci
Project-URL: Documentation, https://mfoci.readthedocs.io
Project-URL: Issue Tracker, https://github.com/Corrram/mfoci/issues
Keywords: finance,markets,analysis
Classifier: Development Status :: 4 - Beta
Classifier: Intended Audience :: Financial and Insurance Industry
Classifier: Intended Audience :: Science/Research
Classifier: Programming Language :: Python :: 3
Classifier: Programming Language :: Python :: 3.10
Classifier: Programming Language :: Python :: 3.11
Classifier: Programming Language :: Python :: 3.12
Classifier: Programming Language :: Python :: 3.13
Classifier: Topic :: Scientific/Engineering :: Information Analysis
Classifier: License :: OSI Approved :: MIT License
Requires-Python: >=3.10
License-File: LICENSE
Requires-Dist: numpy>=2.0
Requires-Dist: pandas>=2.2
Requires-Dist: scikit-learn>=1.4
Requires-Dist: matplotlib>=3.9
Requires-Dist: statsmodels>=0.14
Requires-Dist: jinja2>=3.1
Requires-Dist: yfinance>=0.2
Requires-Dist: tqdm>=4.66
Requires-Dist: twine>=6.1.0
Provides-Extra: dev
Requires-Dist: copul>=0.2.0; extra == "dev"
Requires-Dist: pytest>=8.3.2; extra == "dev"
Requires-Dist: pytest-cov>=5.0.0; extra == "dev"
Requires-Dist: pytest-pycharm>=0.7.0; extra == "dev"
Requires-Dist: pytest-xdist>=3.6.1; extra == "dev"
Requires-Dist: ruff>=0.9.10; extra == "dev"
Requires-Dist: setuptools>=72.1.0; extra == "dev"
Requires-Dist: sphinx>=7.4; extra == "dev"
Requires-Dist: sphinx-rtd-theme>=2.0.0; extra == "dev"
Requires-Dist: twine>=6.1.0; extra == "dev"
Dynamic: license-file
